<?xml version="1.0" encoding="utf-8"?>

<bandas titulo="Information on 6 Bands">
	<apres numAluno="19432" nomeAluno="João Pinto" foto="eu.jpg">
		<par>
			This small app has the objective to depict basic information about 6 bands, "Bastille", "Walk The Moon", "Kaleo", "Of Monsters And Men", "Imagine Dragons" and "TWRP", along with it's members, albuns and songs, released in an official
			 manner. It may not include some off records projects and non comercially released songs.
		</par>
		<par>
			It was designed by the student João Pinto, number 19432.
		</par>
	</apres>
	<banda nome="Bastille" imagem="bastilleImg.jpg">
		<links>
			<link site="Wikipedia" logo="wikipediaLogo.jpg" url="https://en.wikipedia.org/wiki/Bastille_(band)"/>
			<link site="YouTube" logo="youtube.jpg" url="https://www.youtube.com/user/BastilleVEVO"/>
			<link site="Bastille Site" logo="bastilleSite.jpg" url="http://www.bastillebastille.com/"/>
		</links>
		<membros>
			<membro nome="Dan Smith" foto="bastille_danSmith.jpg" dataEntrada="2010" dataSaida="Present">
				<funcao>lead vocals</funcao>
				<funcao>piano</funcao>
				<funcao>keyboards</funcao>
			</membro>
			<membro nome="Chris «Woody» Wood" foto="bastille_woody.jpg" dataEntrada="2010" dataSaida="Present">
				<funcao>drums</funcao>
				<funcao>percussion</funcao>
				<funcao>backing vocals</funcao>
			</membro>
			<membro nome="Kyle Simmons" foto="bastille_kyleSimmons.jpg" dataEntrada="2010" dataSaida="Present">
				<funcao>piano</funcao>
				<funcao>keyboards</funcao>
				<funcao>backing vocals</funcao>
				<funcao>bass</funcao>
				<funcao>guitar</funcao>
			</membro>
			<membro nome="Will Farquarson" foto="bastille_willFarquarson.jpg" dataEntrada="2010" dataSaida="Present">
				<funcao>piano</funcao>
				<funcao>keyboards</funcao>
				<funcao>backing vocals</funcao>
				<funcao>bass</funcao>
				<funcao>guitar</funcao>
			</membro>
		</membros>
		<discografia>
			<album titulo="Bad Blood" imagem="bastille_badBlood.jpg" ano="2013">
				<links>
          <link site="Amazon" logo="amazonLogo.jpg" url="https://www.amazon.com/Bad-Blood-Bastille/dp/B00DV3A84G/ref=sr_1_1?s=music&amp;ie=UTF8&amp;qid=1495451801&amp;sr=1-1&amp;keywords=bad+blood+bastille" />
					<link site="iTunes" logo="iTunes.jpg" url="https://itunes.apple.com/us/album/bad-blood/id672945248" />
				</links>
				<faixas>
					<faixa titulo="Pompei" duracao="214">
						<links>
							<link site="Spotify" logo="spotify.jpg" url="https://open.spotify.com/track/0sooJd5WbNnnz5k6yO7FIQ" />
							<link site="YouTube" logo="youtube.jpg" url="https://www.youtube.com/watch?v=F90Cw4l-8NY" />
						</links>
						<generos>
							<genero>Indie Pop</genero>
							<genero>Synth Pop</genero>
						</generos>
					</faixa>
					<faixa titulo="Things We Lost in the Fire" duracao="241">
						<links>
							<link site="Spotify" logo="spotify.jpg" url="https://open.spotify.com/track/4NX4HZphj4vu36lRtd1COh" />
							<link site="YouTube" logo="youtube.jpg" url="https://www.youtube.com/watch?v=MGR4U7W1dZU" />
						</links>
						<generos>
							<genero>Indie Pop</genero>
						</generos>
					</faixa>
					<faixa titulo="Bad Blood" duracao="212">
						<links>
							<link site="Spotify" logo="spotify.jpg" url="https://open.spotify.com/track/0uGQhIfv5CiXToqBVcdmie" />
							<link site="YouTube" logo="youtube.jpg" url="https://www.youtube.com/watch?v=qoNYlV07Cf8" />
						</links>
						<generos>
							<genero>Indie Pop</genero>
							<genero>Synth Pop</genero>
							<genero>Reggae Fusion</genero>
						</generos>
					</faixa>
					<faixa titulo="Overjoyed" duracao="206">
						<links>
							<link site="Spotify" logo="spotify.jpg" url="https://open.spotify.com/track/6UMtNccUesjuOnNelwUHFV" />
							<link site="YouTube" logo="youtube.jpg" url="https://www.youtube.com/watch?v=fK3fVJtFTh0" />
						</links>
						<generos>
							<genero>Indie Pop</genero>
							<genero>Synth Pop</genero>
						</generos>
					</faixa>
					<faixa titulo="These Streets" duracao="175">
						<links>
							<link site="Spotify" logo="spotify.jpg" url="https://open.spotify.com/track/4AEWFbQ8yq7VjubzkLOtBL" />
							<link site="YouTube" logo="youtube.jpg" url="https://www.youtube.com/watch?v=zEratQ9p7nM" />
						</links>
						<generos>
							<genero>Indie Pop</genero>
							<genero>Synth Pop</genero>
						</generos>
					</faixa>
					<faixa titulo="Weight of Living, Pt. II" duracao="175">
						<links>
							<link site="Spotify" logo="spotify.jpg" url="https://open.spotify.com/track/4uxcMlrKDqXOsNMrqaOVd6" />
							<link site="YouTube" logo="youtube.jpg" url="https://www.youtube.com/watch?v=S_aa5-SHvDY" />
						</links>
						<generos>
							<genero>Indie Pop</genero>
							<genero>Synth Pop</genero>
						</generos>
					</faixa>
					<faixa titulo="Icarus" duracao="225">
						<links>
							<link site="Spotify" logo="spotify.jpg" url="https://open.spotify.com/track/7AO2eDrX9bCURGUiIFdQ0e" />
							<link site="YouTube" logo="youtube.jpg" url="https://www.youtube.com/watch?v=FehA9OwZflw" />
						</links>
						<generos>
							<genero>Indie Pop</genero>
							<genero>Synth Pop</genero>
						</generos>
					</faixa>
					<faixa titulo="Oblivion" duracao="196">
						<links>
							<link site="Spotify" logo="spotify.jpg" url="https://open.spotify.com/track/3nfpiEttnjNGyi0bg0pHwt" />
							<link site="YouTube" logo="youtube.jpg" url="https://www.youtube.com/watch?v=VgXOPeobPcI" />
						</links>
						<generos>
							<genero>Indie Pop</genero>
							<genero>Synth Pop</genero>
						</generos>
					</faixa>
					<faixa titulo="Flaws" duracao="218">
						<links>
							<link site="Spotify" logo="spotify.jpg" url="https://open.spotify.com/track/0XtJgHek9CojyK72X8zWIG" />
							<link site="YouTube" logo="youtube.jpg" url="https://www.youtube.com/watch?v=1E36WU9Wzf4" />
						</links>
						<generos>
							<genero>Synth Pop</genero>
						</generos>
					</faixa>
					<faixa titulo="Daniel in the Den" duracao="183">
						<links>
							<link site="Spotify" logo="spotify.jpg" url="https://open.spotify.com/track/2v3PYJDvbE3JCQ33OMOu3h" />
							<link site="YouTube" logo="youtube.jpg" url="https://www.youtube.com/watch?v=yC_T-KdWCiI" />
						</links>
						<generos>
							<genero>Indie Pop</genero>
							<genero>Synth Pop</genero>
						</generos>
					</faixa>
					<faixa titulo="Laura Palmer" duracao="186">
						<links>
							<link site="Spotify" logo="spotify.jpg" url="https://open.spotify.com/track/1TCdgVHEVd48HKpSdJOYk4" />
							<link site="YouTube" logo="youtube.jpg" url="https://www.youtube.com/watch?v=JQnSc0bczg0" />
						</links>
						<generos>
							<genero>Indie Pop</genero>
						</generos>
					</faixa>
					<faixa titulo="Get Home" duracao="191">
						<links>
							<link site="Spotify" logo="spotify.jpg" url="https://open.spotify.com/track/2SNg9jqsE7mGPuIai9mrFK" />
							<link site="YouTube" logo="youtube.jpg" url="https://www.youtube.com/watch?v=U6-s5RsEmOg" />
						</links>
						<generos>
							<genero>Synth Pop</genero>
						</generos>
					</faixa>
					<faixa titulo="Weight of Living, Pt. I" duracao="206">
						<links>
							<link site="Spotify" logo="spotify.jpg" url="https://open.spotify.com/track/6ODRQ1G3luYlcUtxJmmBgi" />
							<link site="YouTube" logo="youtube.jpg" url="https://www.youtube.com/watch?v=xyzHYg9BYRs" />
						</links>
						<generos>
							<genero>Indie Pop</genero>
							<genero>Synth Pop</genero>
						</generos>
					</faixa>
				</faixas>
			</album>
			<album titulo="VS. (Other People's Heartache, Pt. III)" imagem="bastille_vs.jpg" ano="2014">
				<links>
					<link site="Amazon" logo="amazonLogo.jpg" url="https://www.amazon.co.uk/VS-Other-Peoples-Heartache-Explicit/dp/B00OLBZ8M4" />
					<link site="iTunes" logo="iTunes.jpg" url="https://itunes.apple.com/us/album/vs-other-peoples-heartache-pt-iii/id931281859" />
				</links>
				<faixas>
					<faixa titulo='Fall Into Your Arms (featuring The Gemma Sharples Quartet)' duracao="109">
						<links>
							<link site="Spotify" logo="spotify.jpg" url="https://open.spotify.com/track/0GD65x9bZXa8u16ZKNKhnb" />
							<link site="YouTube" logo="youtube.jpg" url="https://www.youtube.com/watch?v=8Kjaov067QY" />
						</links>
						<generos>
							<genero>Synth Pop</genero>
						</generos>
					</faixa>
					<faixa titulo='Bite Down (featuring HAIM)' duracao="180">
						<links>
							<link site="Spotify" logo="spotify.jpg" url="https://open.spotify.com/track/0mYWBwLXmJBbIBd494YyyR" />
							<link site="YouTube" logo="youtube.jpg" url="https://www.youtube.com/watch?v=WL1WuxL2bMc" />
						</links>
						<generos>
							<genero>Indie Pop</genero>
							<genero>Synth Pop</genero>
						</generos>
					</faixa>
					<faixa titulo="bad_news (featuring MNEK)" duracao="288">
						<links>
							<link site="Spotify" logo="spotify.jpg" url="https://open.spotify.com/track/0uzM3UBcpUiIq8fIQFPDaq" />
							<link site="YouTube" logo="youtube.jpg" url="https://www.youtube.com/watch?v=_dtywPNWqTI" />
						</links>
						<generos>
							<genero>Synth Pop</genero>
						</generos>
					</faixa>
					<faixa titulo="The Driver" duracao="261">
						<links>
							<link site="Spotify" logo="spotify.jpg" url="https://open.spotify.com/track/1u0FClbBEsKwI6vOk9oUmN" />
							<link site="YouTube" logo="youtube.jpg" url="https://www.youtube.com/watch?v=foXqHUopCJU" />
						</links>
						<generos>
							<genero>Indie Pop</genero>
							<genero>Synth Pop</genero>
						</generos>
					</faixa>
					<faixa titulo="Axe to Grind (featuring Tyde and Rationale)" duracao="288">
						<links>
							<link site="Spotify" logo="spotify.jpg" url="https://open.spotify.com/track/1A8GNZEQLkiJzBki0aH0kx" />
							<link site="YouTube" logo="youtube.jpg" url="https://www.youtube.com/watch?v=kVoaGnlHptM" />
						</links>
						<generos>
							<genero>Synth Pop</genero>
						</generos>
					</faixa>
					<faixa titulo="Torn Apart (featuring GRADES)" duracao="186">
						<links>
							<link site="Spotify" logo="spotify.jpg" url="https://open.spotify.com/track/7tMS60qyTwG43P51pmr8gI" />
							<link site="YouTube" logo="youtube.jpg" url="https://www.youtube.com/watch?v=rLrtEyisDMU" />
						</links>
						<generos>
							<genero>Synth Pop</genero>
						</generos>
					</faixa>
					<faixa titulo="Torn Apart, Pt. II (featuring GRADES and Lizzo)" duracao="62">
						<links>
							<link site="Spotify" logo="spotify.jpg" url="https://open.spotify.com/track/6HEsoNHLEunUtC7hD2GoRK" />
							<link site="YouTube" logo="youtube.jpg" url="https://www.youtube.com/watch?v=znQPr0vmhgA" />
						</links>
						<generos>
							<genero>Synth Pop</genero>
						</generos>
					</faixa>
					<faixa titulo="Weapon (Bastille vs. Angel Haze vs. F-U-G-Z)" duracao="288">
						<links>
							<link site="Spotify" logo="spotify.jpg" url="" />
							<link site="YouTube" logo="youtube.jpg" url="" />
						</links>
						<generos>
							<genero>Syth Pop</genero>
							<genero>Rap</genero>
						</generos>
					</faixa>
					<faixa titulo="Remains" duracao="279">
						<links>
							<link site="Spotify" logo="spotify.jpg" url="https://open.spotify.com/track/0XDkORnqAgnWMtqKlouLWT" />
							<link site="YouTube" logo="youtube.jpg" url="https://www.youtube.com/watch?v=bTxx5CfeNg8" />
						</links>
						<generos>
							<genero>Indie Pop</genero>
						</generos>
					</faixa>
				</faixas>
			</album>
			<album titulo="Wild World" imagem="bastille_wildWorld.jpg" ano="2016">
				<links>
					<link site="Amazon" logo="amazonLogo.jpg" url="https://www.amazon.com/Wild-World-Bastille/dp/B01HQZY926" />
					<link site="iTunes" logo="iTunes.jpg" url="https://itunes.apple.com/us/album/wild-world/id1127933001" />
				</links>
				<faixas>
					<faixa titulo="Good Grief" duracao="206">
						<links>
							<link site="Spotify" logo="spotify.jpg" url="https://open.spotify.com/track/6IGA5YrFiEr5ANrMqKkR6H" />
							<link site="YouTube" logo="youtube.jpg" url="https://www.youtube.com/watch?v=ZWCB3hpJDXM" />
						</links>
						<generos>
							<genero>Indie Pop</genero>
						</generos>
					</faixa>
					<faixa titulo="The Currents" duracao="204">
						<links>
							<link site="Spotify" logo="spotify.jpg" url="https://open.spotify.com/track/6F92C7aYYFq0AMQgXzS8o5" />
							<link site="YouTube" logo="youtube.jpg" url="https://www.youtube.com/watch?v=NxM0pRvaDsw" />
						</links>
						<generos>
							<genero>Indie Rock</genero>
						</generos>
					</faixa>
					<faixa titulo="An Act Of Kindness" duracao="208">
						<links>
							<link site="Spotify" logo="spotify.jpg" url="https://open.spotify.com/track/0x2VaCNfT2xoyrcI3wM42S" />
							<link site="YouTube" logo="youtube.jpg" url="https://www.youtube.com/watch?v=VTM4GSJAZQ4" />
						</links>
						<generos>
							<genero>Indie Pop</genero>
							<genero>Synth Pop</genero>
						</generos>
					</faixa>
					<faixa titulo="Warmth" duracao="229">
						<links>
							<link site="Spotify" logo="spotify.jpg" url="https://open.spotify.com/track/6gp4WaJIxgEwgRLvlelmwa" />
							<link site="YouTube" logo="youtube.jpg" url="https://www.youtube.com/watch?v=yKWZsLV5VgA" />
						</links>
						<generos>
							<genero>Indie Pop</genero>
							<genero>Synth Pop</genero>
						</generos>
					</faixa>
					<faixa titulo="Glory" duracao="281">
						<links>
							<link site="Spotify" logo="spotify.jpg" url="https://open.spotify.com/track/43Ihf4Lp2OiH4RLtB78NcN" />
							<link site="YouTube" logo="youtube.jpg" url="https://www.youtube.com/watch?v=zxJCMOMx550" />
						</links>
						<generos>
							<genero>Indie Pop</genero>
						</generos>
					</faixa>
					<faixa titulo="Power" duracao="209">
						<links>
							<link site="Spotify" logo="spotify.jpg" url="https://open.spotify.com/track/0xvheQU4o81CSf8BRTI90A" />
							<link site="YouTube" logo="youtube.jpg" url="https://www.youtube.com/watch?v=H1WmNkobGC4" />
						</links>
						<generos>
							<genero>Indie Pop</genero>
							<genero>Synth Pop</genero>
						</generos>
					</faixa>
					<faixa titulo="Two Evils" duracao="226">
						<links>
							<link site="Spotify" logo="spotify.jpg" url="https://open.spotify.com/track/15P9zM3pGP4yXO5wTKkJ7Z" />
							<link site="YouTube" logo="youtube.jpg" url="https://www.youtube.com/watch?v=pcqgF2CV_7Y" />
						</links>
						<generos>
							<genero>Indie Rock</genero>
						</generos>
					</faixa>
					<faixa titulo="Send Them Off!" duracao="200">
						<links>
							<link site="Spotify" logo="spotify.jpg" url="https://open.spotify.com/track/2Pf6Lix1tixacmos5pvCOw" />
							<link site="YouTube" logo="youtube.jpg" url="https://www.youtube.com/watch?v=vn-6fiVkAcA" />
						</links>
						<generos>
							<genero>Indie Rock</genero>
						</generos>
					</faixa>
					<faixa titulo="Lethargy" duracao="224">
						<links>
							<link site="Spotify" logo="spotify.jpg" url="https://open.spotify.com/track/3QVGEHyj4IhoDkiFHktzvT" />
							<link site="YouTube" logo="youtube.jpg" url="https://www.youtube.com/watch?v=crp-pYZlHZc" />
						</links>
						<generos>
							<genero>Indie Pop</genero>
							<genero>Indie Rock</genero>
						</generos>
					</faixa>
					<faixa titulo="Four Walls (The Ballad Of Perry Smith)" duracao="254">
						<links>
							<link site="Spotify" logo="spotify.jpg" url="https://open.spotify.com/track/1Lczbl4rrFN91IcyidUqqC" />
							<link site="YouTube" logo="youtube.jpg" url="https://www.youtube.com/watch?v=TUdbuK_7lUE" />
						</links>
						<generos>
							<genero>Indie Rock</genero>
						</generos>
					</faixa>
					<faixa titulo="Blame" duracao="235">
						<links>
							<link site="Spotify" logo="spotify.jpg" url="https://open.spotify.com/track/0Cl5kShLrsbvLxuwfIBEnT" />
							<link site="YouTube" logo="youtube.jpg" url="https://www.youtube.com/watch?v=nAGEtmnXsiY" />
						</links>
						<generos>
							<genero>Indie Rock</genero>
						</generos>
					</faixa>
					<faixa titulo="Fake It" duracao="244">
						<links>
							<link site="Spotify" logo="spotify.jpg" url="https://open.spotify.com/track/5qS17rR9HlqZvbQwssTzlX" />
							<link site="YouTube" logo="youtube.jpg" url="https://www.youtube.com/watch?v=GIwyqsqHsic" />
						</links>
						<generos>
							<genero>Eletro Pop</genero>
							<genero>Alternative Dance</genero>
							<genero>Synth Pop</genero>
						</generos>
					</faixa>
					<faixa titulo="Snakes" duracao="197">
						<links>
							<link site="Spotify" logo="spotify.jpg" url="https://open.spotify.com/track/5g1EONU0jM4TuTznKxGirt" />
							<link site="YouTube" logo="youtube.jpg" url="https://www.youtube.com/watch?v=L7g_E_rJc40" />
						</links>
						<generos>
							<genero>Indie Pop</genero>
							<genero>Synth Pop</genero>
						</generos>
					</faixa>
					<faixa titulo="Winter of our Youth" duracao="203">
						<links>
							<link site="Spotify" logo="spotify.jpg" url="https://open.spotify.com/track/0orRfRjSE3h7vOEdQ4VSPH" />
							<link site="YouTube" logo="youtube.jpg" url="https://www.youtube.com/watch?v=5XBtTa1E94M" />
						</links>
						<generos>
							<genero>Indie Rock</genero>
							<genero>Indie Pop</genero>
						</generos>
					</faixa>
				</faixas>
			</album>
		</discografia>
		<biografia>
			<par>
			Bastille (stylised as BΔSTILLE) are a British indie pop band formed in 2010. The group began as a solo project by lead vocalist Dan Smith,
			but later expanded to include keyboardist Kyle Simmons, bassist and guitarist Will Farquarson, and drummer Chris Wood. The name of the band derives
			from Bastille Day, which is celebrated on 14 July, the date of Smith's birthday.
			</par>
			<par>
			After an independently released debut single and a self-released EP, the band signed to Virgin Records. Their first studio album, Bad Blood, was released
			in March 2013 and entered the UK Albums Chart at number one. The band was nominated for four Brit Awards at the 2014 ceremony, winning the British Breakthrough Act.
			As of November 2014, Bastille have sold over 5 million records in the US and 2.5 million records in the UK.
			</par>
		</biografia>
	</banda>
  <banda nome="Walk the Moon" imagem="walkTheMoon.jpg">
    <links>
      <link site="Wikipedia" logo="wikipediaLogo.jpg" url="https://en.wikipedia.org/wiki/Walk_the_Moon" />
      <link site="YouTube" logo="youtube.jpg" url="https://www.youtube.com/user/WalkTheMoonVEVO" />
      <link site="Walk the Moon Site" logo="walkTheMoonLogo.jpg" url="http://www.walkthemoonband.com/" />
    </links>
    <membros>
      <membro nome="Nicholas Petricca" foto="nick_WTM.jpg" dataEntrada="2008" dataSaida="Present">
        <funcao>lead vocals</funcao>
        <funcao>keyboards</funcao>
        <funcao>synthesizer</funcao>
      </membro>
      <membro nome="Kevin Ray" foto="kevin_WTM.jpg" dataEntrada="2010" dataSaida="Present">
        <funcao>bass</funcao>
        <funcao>backing vocals</funcao>
        <funcao>guitar</funcao>
      </membro>
      <membro nome="Sean Waugaman" foto="sean_WTM.jpg" dataEntrada="2010" dataSaida="Present">
        <funcao>drums</funcao>
        <funcao>backing vocals</funcao>
      </membro>
      <membro nome="Eli Maiman" foto="eli_WTM.jpg" dataEntrada="2011" dataSaida="Present">
        <funcao>guitar</funcao>
        <funcao>backing vocals</funcao>
      </membro>
    </membros>
    <discografia>
      <album titulo="Walk the Moon" imagem="walkTheMoon_WTM.jpg" ano="2012" editora="RCA">
        <links>
          <link site="Amazon" logo="amazonLogo.jpg" url="https://www.amazon.com/Walk-Moon/dp/B007VDWGJW/ref=ntt_mus_ep_dpi_2" />
          <link site="iTunes" logo="iTunes.jpg" url="https://itunes.apple.com/us/album/id533488692?i=533488700" />
        </links>
        <faixas>
          <faixa titulo="Quesadilla" duracao="195">
            <links>
              <link site="Spotify" logo="spotify.jpg" url="https://open.spotify.com/track/2CdNHP8DJ5tfbRoIRdcTeE" />
              <link site="YouTube" logo="youtube.jpg" url="https://www.youtube.com/watch?v=98jijv5-xOg" />
            </links>
            <generos>
              <genero>Alternative</genero>
              <genero>Indie</genero>
            </generos>
          </faixa>
          <faixa titulo="Lisa Baby" duracao="232">
            <links>
              <link site="Spotify" logo="spotify.jpg" url="https://open.spotify.com/track/0obyZJdAvDvhtvudGsNjvS" />
              <link site="YouTube" logo="youtube.jpg" url="https://www.youtube.com/watch?v=4cqCpPSaY-I" />
            </links>
            <generos>
              <genero>Alternative</genero>
              <genero>Indie</genero>
            </generos>
          </faixa>
          <faixa titulo="Next in Line" duracao="239">
            <links>
              <link site="Spotify" logo="spotify.jpg" url="https://open.spotify.com/track/2RSVYvx9kGLbyyJ4bmRMbc" />
              <link site="YouTube" logo="youtube.jpg" url="https://www.youtube.com/watch?v=9RAPtw_FkDo" />
            </links>
            <generos>
              <genero>Alternative</genero>
              <genero>Indie</genero>
            </generos>
          </faixa>
          <faixa titulo="Anna Sun" duracao="321">
            <links>
              <link site="Spotify" logo="spotify.jpg" url="https://open.spotify.com/track/3e0yTP5trHBBVvV32jwXqF" />
              <link site="YouTube" logo="youtube.jpg" url="https://www.youtube.com/watch?v=qDVW81bXo0s" />
            </links>
            <generos>
              <genero>Alternative</genero>
              <genero>Indie</genero>
            </generos>
          </faixa>
          <faixa titulo="Tightrope" duracao="209">
            <links>
              <link site="Spotify" logo="spotify.jpg" url="https://open.spotify.com/track/44psOy0D0SP8rcIiUgKgBs" />
              <link site="YouTube" logo="youtube.jpg" url="https://www.youtube.com/watch?v=gPedH9B8AAE" />
            </links>
            <generos>
              <genero>Alternative</genero>
              <genero>Indie</genero>
            </generos>
          </faixa>
          <faixa titulo="Jenny" duracao="245">
            <links>
              <link site="Spotify" logo="spotify.jpg" url="https://open.spotify.com/track/7eMpW9I1ZpVs6VQ90naDBh" />
              <link site="YouTube" logo="youtube.jpg" url="https://www.youtube.com/watch?v=I7ar0wdK4vc" />
            </links>
            <generos>
              <genero>Alternative</genero>
              <genero>Indie</genero>
            </generos>
          </faixa>
          <faixa titulo="Shiver Shiver" duracao="238">
            <links>
              <link site="Spotify" logo="spotify.jpg" url="https://open.spotify.com/track/4LgIcna8LRrR3DOomihYMY" />
              <link site="YouTube" logo="youtube.jpg" url="https://www.youtube.com/watch?v=uD63wVc57A8" />
            </links>
            <generos>
              <genero>Alternative</genero>
              <genero>Indie</genero>
            </generos>
          </faixa>
          <faixa titulo="Lion" duracao="35">
            <links>
              <link site="Spotify" logo="spotify.jpg" url="https://open.spotify.com/track/2gzDs0aRWhNdDVvFTL28gS" />
              <link site="YouTube" logo="youtube.jpg" url="https://www.youtube.com/watch?v=D8Gk5BXdU1Y" />
            </links>
            <generos>
              <genero>Alternative</genero>
              <genero>Indie</genero>
            </generos>
          </faixa>
          <faixa titulo="Iscariot" duracao="323">
            <links>
              <link site="Spotify" logo="spotify.jpg" url="https://open.spotify.com/track/5urdl721ncXAFkuIwR9Mj5" />
              <link site="YouTube" logo="youtube.jpg" url="https://www.youtube.com/watch?v=fPQeMqiKqKs" />
            </links>
            <generos>
              <genero>Alternative</genero>
              <genero>Indie</genero>
            </generos>
          </faixa>
          <faixa titulo="Fixin'" duracao="262">
            <links>
              <link site="Spotify" logo="spotify.jpg" url="https://open.spotify.com/track/5YJZgqCK7sgr07YZJOnfTY" />
              <link site="YouTube" logo="youtube.jpg" url="https://www.youtube.com/watch?v=8w0wFcByqs0" />
            </links>
            <generos>
              <genero>Alternative</genero>
              <genero>Indie</genero>
            </generos>
          </faixa>
          <faixa titulo="I Can Lift a Car" duracao="228">
            <links>
              <link site="Spotify" logo="spotify.jpg" url="https://open.spotify.com/track/6v6S5TvOsrPofUWst04BLF" />
              <link site="YouTube" logo="youtube.jpg" url="https://www.youtube.com/watch?v=Q03YOKrLTPo" />
            </links>
            <generos>
              <genero>Alternative</genero>
              <genero>Indie</genero>
            </generos>
          </faixa>
        </faixas>
      </album>
      <album titulo="Talking is Hard" imagem="talkingIsHard_WTM.jpg" ano="2014" editora="	RCA">
        <links>
          <link site="Amazon" logo="amazonLogo.jpg" url="https://www.amazon.com/TALKING-HARD-Walk-Moon/dp/B00OTLFGIM" />
          <link site="iTunes" logo="iTunes.jpg" url="https://itunes.apple.com/us/album/talking-is-hard/id936832274" />
        </links>
        <faixas>
          <faixa titulo="Different Colors" duracao="222">
            <links>
              <link site="Spotify" logo="spotify.jpg" url="https://open.spotify.com/track/3RRRDZig4RNJhVGfwwOOFZ" />
              <link site="YouTube" logo="youtube.jpg" url="https://www.youtube.com/watch?v=2QjqCJOPu-M" />
            </links>
            <generos>
              <genero>Alternative</genero>
              <genero>Indie</genero>
            </generos>
          </faixa>
          <faixa titulo="Sidekick" duracao="175">
            <links>
              <link site="Spotify" logo="spotify.jpg" url="https://open.spotify.com/track/4is9iORYOEafLbo79ODEkO" />
              <link site="YouTube" logo="youtube.jpg" url="https://www.youtube.com/watch?v=NXtLryriWeM" />
            </links>
            <generos>
              <genero>Alternative</genero>
              <genero>Indie</genero>
            </generos>
          </faixa>
          <faixa titulo="Shut Up And Dance" duracao="199">
            <links>
              <link site="Spotify" logo="spotify.jpg" url="https://open.spotify.com/track/4kbj5MwxO1bq9wjT5g9HaA" />
              <link site="YouTube" logo="youtube.jpg" url="https://www.youtube.com/watch?v=6JCLY0Rlx6Q" />
            </links>
            <generos>
              <genero>Alternative</genero>
              <genero>Indie</genero>
            </generos>
          </faixa>
          <faixa titulo="Up2U" duracao="201">
            <links>
              <link site="Spotify" logo="spotify.jpg" url="https://open.spotify.com/track/5OWZ4qbW7bYQTGIKRbSvxA" />
              <link site="YouTube" logo="youtube.jpg" url="https://www.youtube.com/watch?v=p4JMFtGCInM" />
            </links>
            <generos>
              <genero>Alternative</genero>
              <genero>Indie</genero>
            </generos>
          </faixa>
          <faixa titulo="Avalanche" duracao="218">
            <links>
              <link site="Spotify" logo="spotify.jpg" url="https://open.spotify.com/track/3JxaZPq4UjkOaxnpyMUtAC" />
              <link site="YouTube" logo="youtube.jpg" url="https://www.youtube.com/watch?v=ECBhz_1AaSM" />
            </links>
            <generos>
              <genero>Alternative</genero>
              <genero>Indie</genero>
            </generos>
          </faixa>
          <faixa titulo="Portugal" duracao="241">
            <links>
              <link site="Spotify" logo="spotify.jpg" url="https://open.spotify.com/track/3MYWKl8ScgDu3sAvyneMCG" />
              <link site="YouTube" logo="youtube.jpg" url="https://www.youtube.com/watch?v=X2_G9mfd2zY" />
            </links>
            <generos>
              <genero>Alternative</genero>
              <genero>Indie</genero>
            </generos>
          </faixa>
          <faixa titulo="Down in the Dumps" duracao="285">
            <links>
              <link site="Spotify" logo="spotify.jpg" url="https://open.spotify.com/track/40fCroW8wu8TdmW9A7k17z" />
              <link site="YouTube" logo="youtube.jpg" url="https://www.youtube.com/watch?v=WBLA0YQynFM" />
            </links>
            <generos>
              <genero>Alternative</genero>
              <genero>Indie</genero>
            </generos>
          </faixa>
          <faixa titulo="Work This Body" duracao="175">
            <links>
              <link site="Spotify" logo="spotify.jpg" url="https://open.spotify.com/track/76EeScTnI2sCjDY0SfEoSb" />
              <link site="YouTube" logo="youtube.jpg" url="https://www.youtube.com/watch?v=qzkCk6-d8Oc" />
            </links>
            <generos>
              <genero>Alternative</genero>
              <genero>Indie</genero>
            </generos>
          </faixa>
          <faixa titulo="Work This Body" duracao="175">
            <links>
              <link site="Spotify" logo="spotify.jpg" url="https://open.spotify.com/track/76EeScTnI2sCjDY0SfEoSb" />
              <link site="YouTube" logo="youtube.jpg" url="https://www.youtube.com/watch?v=qzkCk6-d8Oc" />
            </links>
            <generos>
              <genero>Alternative</genero>
              <genero>Indie</genero>
            </generos>
          </faixa>
          <faixa titulo="Spend Your $$$" duracao="202">
            <links>
              <link site="Spotify" logo="spotify.jpg" url="https://open.spotify.com/track/4crempk25OrH2OZqarABqv" />
              <link site="YouTube" logo="youtube.jpg" url="https://www.youtube.com/watch?v=N_b2dFsEVhc" />
            </links>
            <generos>
              <genero>Alternative</genero>
              <genero>Indie</genero>
            </generos>
          </faixa>
          <faixa titulo="We Are The Kids" duracao="217">
            <links>
              <link site="Spotify" logo="spotify.jpg" url="https://open.spotify.com/track/24Rl1EUg5y9uym2rI3DL3r" />
              <link site="YouTube" logo="youtube.jpg" url="https://www.youtube.com/watch?v=HnQS0FGaBbg" />
            </links>
            <generos>
              <genero>Alternative</genero>
              <genero>Indie</genero>
            </generos>
          </faixa>
          <faixa titulo="Come Under The Covers" duracao="231">
            <links>
              <link site="Spotify" logo="spotify.jpg" url="https://open.spotify.com/track/3RBLfzw7SoyiAcOncA37De" />
              <link site="YouTube" logo="youtube.jpg" url="https://www.youtube.com/watch?v=xsT4V2o1gHQ" />
            </links>
            <generos>
              <genero>Alternative</genero>
              <genero>Indie</genero>
            </generos>
          </faixa>
          <faixa titulo="Aquaman" duracao="240">
            <links>
              <link site="Spotify" logo="spotify.jpg" url="https://open.spotify.com/track/71wT7aMCFPYfzutF66OLac" />
              <link site="YouTube" logo="youtube.jpg" url="https://www.youtube.com/watch?v=VRVgptW7bYg" />
            </links>
            <generos>
              <genero>Alternative</genero>
              <genero>Indie</genero>
            </generos>
          </faixa>
        </faixas>
      </album>
    </discografia>
    <biografia>
      <par>
        Walk The Moon (styled WALK THE MOON) is an American rock band based in Cincinnati, Ohio. Lead singer Nicholas Petricca started the band in 2006, while a student at Kenyon College, deriving the band's name from the song "Walking on the Moon" by The Police. The group independently released their debut studio album, i want, i want, in November 2010, receiving airplay for the track "Anna Sun" on multiple Alternative radio stations. Along with the success of Anna Sun, Alt. Nation named them a band you need to know for the Summer of 2012. Influential music blog Neon Gold helped to break the band in January 2011, calling Anna Sun "the kind of stuff British A and R dreams, and major label bidding wars, are made of."
      </par>
      <par>
        In February 2011, they signed to RCA Records and in June 2012 released their first major label studio album, Walk the Moon which includes a re-recorded version of Anna Sun from i want!, i want!, which was song of the summer at least two years in a row. In December 2014, the band released their second major-label studio album, Talking Is Hard. This album includes the song "Shut Up and Dance," which hit number 4 on the Billboard Hot 100 and reached number one on the Billboard Rock Songs chart and Billboard Alternative Songs chart. Ryan Seed of Billboard gave "Shut Up and Dance" four and a half stars out of five.
      </par>
    </biografia>
  </banda>
  <banda nome="Kaleo" imagem="kaleo.jpg">
    <links>
      <link site="Wikipedia" logo="wikipediaLogo.jpg" url="https://en.wikipedia.org/wiki/Kaleo_(band)" />
      <link site="YouTube" logo="youtube.jpg" url="https://www.youtube.com/user/Kaleoofficial?spfreload=1" />
      <link site="Kaleo Site" logo="KaleoLogo.jpg" url="http://www.officialkaleo.com/" />
    </links>
    <membros>
      <membro nome="JJ Julius Son" foto="jj_Kaleo.jpg" dataEntrada="2012" dataSaida="Present">
        <funcao>lead vocals</funcao>
        <funcao>rhythm guitar</funcao>
        <funcao>piano</funcao>
      </membro>
      <membro nome="Rubin Pollock" foto="rubin_Kaleo.jpg" dataEntrada="2012" dataSaida="Present">
        <funcao>lead guitar</funcao>
        <funcao>backing vocals</funcao>
      </membro>
      <membro nome="Daniel Kristjansson" foto="daniel_Kaleo.jpg" dataEntrada="2012" dataSaida="Present">
        <funcao>bass</funcao>
      </membro>
      <membro nome="David Antonsson" foto="david_Kaleo.jpg" dataEntrada="2012" dataSaida="Present">
        <funcao>drums</funcao>
        <funcao>percussion</funcao>
        <funcao>backing vocals</funcao>
      </membro>
    </membros>
    <discografia>
      <album titulo="A/B" imagem="ab_Kaleo.jpg" ano="2016" editora="Elektra">
        <links>
          <link site="Amazon" logo="amazonLogo.jpg" url="https://www.amazon.com/B-Kaleo/dp/B01EU0HIVO" />
          <link site="iTunes" logo="iTunes.jpg" url="https://itunes.apple.com/br/album/a-b/id1107254993" />
        </links>
        <faixas>
          <faixa titulo="No Good" duracao="246">
            <links>
              <link site="Spotify" logo="spotify.jpg" url="https://open.spotify.com/track/0Tr5G2mE56eLUGvCaXRM8I" />
              <link site="YouTube" logo="youtube.jpg" url="https://www.youtube.com/watch?v=HC6QJsxRypQ" />
            </links>
            <generos>
              <genero>Alternative</genero>
              <genero>Rock</genero>
            </generos>
          </faixa>
          <faixa titulo="No Good" duracao="246">
            <links>
              <link site="Spotify" logo="spotify.jpg" url="https://open.spotify.com/track/0Tr5G2mE56eLUGvCaXRM8I" />
              <link site="YouTube" logo="youtube.jpg" url="https://www.youtube.com/watch?v=HC6QJsxRypQ" />
            </links>
            <generos>
              <genero>Alternative</genero>
              <genero>Rock</genero>
            </generos>
          </faixa>
          <faixa titulo="Way Down We Go" duracao="219">
            <links>
              <link site="Spotify" logo="spotify.jpg" url="https://open.spotify.com/track/0y1QJc3SJVPKJ1OvFmFqe6" />
              <link site="YouTube" logo="youtube.jpg" url="https://www.youtube.com/watch?v=0-7IHOXkiV8" />
            </links>
            <generos>
              <genero>Alternative</genero>
              <genero>Indie</genero>
              <genero>Rock</genero>
            </generos>
          </faixa>
          <faixa titulo="Broken Bones" duracao="245">
            <links>
              <link site="Spotify" logo="spotify.jpg" url="https://open.spotify.com/track/0lwUIYJfWGB8qUEAJtYfb6" />
              <link site="YouTube" logo="youtube.jpg" url="https://www.youtube.com/watch?v=NOletMMI0B4" />
            </links>
            <generos>
              <genero>Alternative</genero>
              <genero>Blues</genero>
              <genero>Rock</genero>
            </generos>
          </faixa>
          <faixa titulo="Broken Bones" duracao="245">
            <links>
              <link site="Spotify" logo="spotify.jpg" url="https://open.spotify.com/track/0lwUIYJfWGB8qUEAJtYfb6" />
              <link site="YouTube" logo="youtube.jpg" url="https://www.youtube.com/watch?v=NOletMMI0B4" />
            </links>
            <generos>
              <genero>Alternative</genero>
              <genero>Blues</genero>
              <genero>Rock</genero>
            </generos>
          </faixa>
          <faixa titulo="Glass House" duracao="241">
            <links>
              <link site="Spotify" logo="spotify.jpg" url="https://open.spotify.com/track/0lwUIYJfWGB8qUEAJtYfb6" />
              <link site="YouTube" logo="youtube.jpg" url="https://www.youtube.com/watch?v=shSKvEp3HFo" />
            </links>
            <generos>
              <genero>Alternative</genero>
              <genero>Rock</genero>
            </generos>
          </faixa>
          <faixa titulo="Hot Blood" duracao="218">
            <links>
              <link site="Spotify" logo="spotify.jpg" url="https://open.spotify.com/track/7d9sZF7jmepe2EYdETlNWK" />
              <link site="YouTube" logo="youtube.jpg" url="https://www.youtube.com/watch?v=p6PuTFmn_ds" />
            </links>
            <generos>
              <genero>Alternative</genero>
              <genero>Indie</genero>
              <genero>Rock</genero>
            </generos>
          </faixa>
          <faixa titulo="All The Pretty Girls" duracao="269">
            <links>
              <link site="Spotify" logo="spotify.jpg" url="https://open.spotify.com/track/0QQIhT6PtJ5glyn4HKNKQ6" />
              <link site="YouTube" logo="youtube.jpg" url="https://www.youtube.com/watch?v=FNwgOkl5nRY" />
            </links>
            <generos>
              <genero>Alternative</genero>
              <genero>Indie</genero>
              <genero>Blues</genero>
            </generos>
          </faixa>
          <faixa titulo="Automobile" duracao="186">
            <links>
              <link site="Spotify" logo="spotify.jpg" url="https://open.spotify.com/track/1bloF1LHgUVvPJLxrzxgu7" />
              <link site="YouTube" logo="youtube.jpg" url="https://www.youtube.com/watch?v=zcUYLAc6tZo" />
            </links>
            <generos>
              <genero>Alternative</genero>
              <genero>Indie</genero>
              <genero>Blues</genero>
              <genero>Country</genero>
            </generos>
          </faixa>
          <faixa titulo="Vor í Vaglaskógi" duracao="277">
            <links>
              <link site="Spotify" logo="spotify.jpg" url="https://open.spotify.com/track/2OdpZeTpnbqPqBrclk2pib" />
              <link site="YouTube" logo="youtube.jpg" url="https://www.youtube.com/watch?v=Da5qQD_RpEQ" />
            </links>
            <generos>
              <genero>Alternative</genero>
              <genero>Indie</genero>
              <genero>Blues</genero>
              <genero>Folk</genero>
            </generos>
          </faixa>
          <faixa titulo="Save Yourself" duracao="273">
            <links>
              <link site="Spotify" logo="spotify.jpg" url="https://open.spotify.com/track/2AwPXDmMeUJGt2Ro5Ea10G" />
              <link site="YouTube" logo="youtube.jpg" url="https://www.youtube.com/watch?v=oCi0RHLrauU" />
            </links>
            <generos>
              <genero>Alternative</genero>
              <genero>Indie</genero>
              <genero>Blues</genero>
            </generos>
          </faixa>
          <faixa titulo="I Can't Go On Without You" duracao="377">
            <links>
              <link site="Spotify" logo="spotify.jpg" url="https://open.spotify.com/track/1dX6oGAG5PaexuPj29PsYd" />
              <link site="YouTube" logo="youtube.jpg" url="https://www.youtube.com/watch?v=jfNOdsvMke4" />
            </links>
            <generos>
              <genero>Alternative</genero>
              <genero>Indie</genero>
              <genero>Rock</genero>
            </generos>
          </faixa>
        </faixas>
      </album>
    </discografia>
    <biografia>
      <par>
        Kaleo is an Icelandic blues/rock band that formed at Mosfellsbær in 2012. It consists of lead vocalist and guitarist JJ Julius Son (Jökull Júlíusson), drummer David Antonsson, bassist Daniel Kristjansson, and lead guitarist Rubin Pollock. They have released two studio albums, Kaleo (2013) and A/B (2016), as well as an EP, Glasshouse (2013). A/B has sold over 175,000 albums worldwide. One of the singles from A/B, "Way Down We Go", has been sold over 500,000 times in the US and reached #1 on the Billboard Alternative Chart on August 20, 2016.
      </par>
      <par>
        The group has made multiple appearances on late night television shows including Conan, Jimmy Kimmel Live!, and Late Night with Seth Meyers. Their songs have been heard on many other television shows including Orange is the New Black, Blindspot, Suits, Vinyl, Grey's Anatomy, Empire, The Leftovers, Frequency, Supergirl, Lucifer (TV series), "Longmire (TV Series)", The Vampire Diaries, and Frontier. "Way Down We Go" was featured in a no7 Skincare ad in the UK and in the second trailer for the film Logan.
      </par>
    </biografia>
  </banda>
  <banda nome="Of Monsters And Men" imagem="omam.jpg">
    <links>
      <link site="Wikipedia" logo="wikipediaLogo.jpg" url="https://en.wikipedia.org/wiki/Of_Monsters_and_Men" />
      <link site="YouTube" logo="youtube.jpg" url="https://www.youtube.com/user/OfMonstersAndMenVEVO" />
      <link site="OMAM Site" logo="omamLogo.jpg" url="http://www.ofmonstersandmen.com/" />
    </links>
    <membros>
      <membro nome="Nanna Bryndís Hilmarsdóttir" foto="nana_OMAM.jpg" dataEntrada="2010" dataSaida="Present">
        <funcao>lead vocals</funcao>
        <funcao>acoustic guitar</funcao>
        <funcao>piano</funcao>
      </membro>
      <membro nome="Ragnar Þórhallsson" foto="ragnar_OMAM.jpg" dataEntrada="2010" dataSaida="Present">
        <funcao>lead vocals</funcao>
        <funcao>acoustic guitar</funcao>
        <funcao>melodica</funcao>
        <funcao>glockenspiel</funcao>
      </membro>
      <membro nome="Brynjar Leifsson" foto="brynjar_OMAM.jpg" dataEntrada="2010" dataSaida="Present">
        <funcao>lead guitar</funcao>
        <funcao>acoustic guitar</funcao>
        <funcao>baritone guitar</funcao>
        <funcao>12-string acoustic guitar</funcao>
        <funcao>melodica</funcao>
        <funcao>backing vocals</funcao>
      </membro>
      <membro nome="Kristján Páll Kristjánsson" foto="kris_OMAM.jpg" dataEntrada="2010" dataSaida="Present">
        <funcao>bass</funcao>
        <funcao>acoustic bass guitar</funcao>
        <funcao>egg shaker</funcao>
        <funcao>backing vocals</funcao>
      </membro>
      <membro nome="Arnar Rósenkranz Hilmarsson" foto="arnar_OMAM.jpg" dataEntrada="2010" dataSaida="Present">
        <funcao>drums</funcao>
        <funcao>percussion</funcao>
        <funcao>melodica</funcao>
        <funcao>glockenspiel</funcao>
        <funcao>accordion</funcao>
        <funcao>keyboard</funcao>
        <funcao>piano</funcao>
        <funcao>acoustic guitar</funcao>
        <funcao>backing vocals</funcao>
      </membro>
      <membro nome="Árni Guðjónsson" foto="arni_OMAM.jpg" dataEntrada="2010" dataSaida="2012">
        <funcao>accordion</funcao>
        <funcao>piano</funcao>
        <funcao>organ</funcao>
        <funcao>keyboards</funcao>
        <funcao>backing vocals</funcao>
      </membro>
    </membros>
    <discografia>
      <album titulo="My Head Is An Animal" imagem="headIsAnAnimal_OMAM.jpg" ano="2012" editora="Republic">
        <links>
          <link site="Amazon" logo="amazonLogo.jpg" url="https://www.amazon.com/My-Head-Animal-Monsters-Men/dp/B007DIQC90" />
          <link site="iTunes" logo="iTunes.jpg" url="https://itunes.apple.com/us/album/my-head-is-an-animal/id509345651" />
        </links>
        <faixas>
          <faixa titulo="Dirty Paws" duracao="278">
            <links>
              <link site="Spotify" logo="spotify.jpg" url="https://open.spotify.com/track/5g7rJvWYVrloJZwKiShqlS" />
              <link site="YouTube" logo="youtube.jpg" url="https://www.youtube.com/watch?v=mCHUw7ACS8o" />
            </links>
            <generos>
              <genero>Rock</genero>
              <genero>Alternative</genero>
              <genero>Folk</genero>
            </generos>
          </faixa>
          <faixa titulo="King and Lionheart" duracao="273">
            <links>
              <link site="Spotify" logo="spotify.jpg" url="https://open.spotify.com/track/310d8Vawp5kYDYrGrrTAzl" />
              <link site="YouTube" logo="youtube.jpg" url="https://www.youtube.com/watch?v=A76a_LNIYwE" />
            </links>
            <generos>
              <genero>Rock</genero>
              <genero>Alternative</genero>
              <genero>Folk</genero>
            </generos>
          </faixa>
          <faixa titulo="Mountain Sound" duracao="211">
            <links>
              <link site="Spotify" logo="spotify.jpg" url="https://open.spotify.com/track/3SPVZJzf1Hs30rB6yXVf2y" />
              <link site="YouTube" logo="youtube.jpg" url="https://www.youtube.com/watch?v=qt7ox1M_XG4" />
            </links>
            <generos>
              <genero>Rock</genero>
              <genero>Alternative</genero>
              <genero>Folk</genero>
            </generos>
          </faixa>
          <faixa titulo="Slow and Steady" duracao="301">
            <links>
              <link site="Spotify" logo="spotify.jpg" url="https://open.spotify.com/track/3raHUAfQyQ7Gv8yK62AVhV" />
              <link site="YouTube" logo="youtube.jpg" url="https://www.youtube.com/watch?v=uRyRymflxtU" />
            </links>
            <generos>
              <genero>Rock</genero>
              <genero>Alternative</genero>
              <genero>Folk</genero>
            </generos>
          </faixa>
          <faixa titulo="From Finner" duracao="223">
            <links>
              <link site="Spotify" logo="spotify.jpg" url="https://open.spotify.com/track/16oGsGvhNhTihlZAYLp2wm" />
              <link site="YouTube" logo="youtube.jpg" url="https://www.youtube.com/watch?v=H7Gr6HBMDu0" />
            </links>
            <generos>
              <genero>Indie</genero>
              <genero>Alternative</genero>
              <genero>Folk</genero>
            </generos>
          </faixa>
          <faixa titulo="Little Talks" duracao="226">
            <links>
              <link site="Spotify" logo="spotify.jpg" url="https://open.spotify.com/track/2ihCaVdNZmnHZWt0fvAM7B" />
              <link site="YouTube" logo="youtube.jpg" url="https://www.youtube.com/watch?v=ghb6eDopW8I" />
            </links>
            <generos>
              <genero>Indie</genero>
              <genero>Alternative</genero>
              <genero>Folk</genero>
            </generos>
          </faixa>
          <faixa titulo="Six Weeks" duracao="334">
            <links>
              <link site="Spotify" logo="spotify.jpg" url="https://open.spotify.com/track/29uPSxuWuR6Hr1SUu2Cw6z" />
              <link site="YouTube" logo="youtube.jpg" url="https://www.youtube.com/watch?v=18Gyci5tw74" />
            </links>
            <generos>
              <genero>Rock</genero>
              <genero>Indie</genero>
              <genero>Alternative</genero>
              <genero>Folk</genero>
            </generos>
          </faixa>
          <faixa titulo="Love Love Love" duracao="232">
            <links>
              <link site="Spotify" logo="spotify.jpg" url="hthttps://open.spotify.com/track/3o1cohFfwd57rAvrbyVE5e" />
              <link site="YouTube" logo="youtube.jpg" url="https://www.youtube.com/watch?v=beiPP_MGz6I" />
            </links>
            <generos>
              <genero>Indie</genero>
              <genero>Alternative</genero>
              <genero>Folk</genero>
            </generos>
          </faixa>
          <faixa titulo="Your Bones" duracao="249">
            <links>
              <link site="Spotify" logo="spotify.jpg" url="https://open.spotify.com/track/3ewKQAIFCLDk0mbhV0HjWE" />
              <link site="YouTube" logo="youtube.jpg" url="https://www.youtube.com/watch?v=wXUloVYbchg" />
            </links>
            <generos>
              <generos>Rock</generos>
              <genero>Indie</genero>
              <genero>Alternative</genero>
              <genero>Folk</genero>
            </generos>
          </faixa>
          <faixa titulo="Sloom" duracao="283">
            <links>
              <link site="Spotify" logo="spotify.jpg" url="https://open.spotify.com/track/6xFxmcebq5XphN0WoxNLgp" />
              <link site="YouTube" logo="youtube.jpg" url="https://www.youtube.com/watch?v=FubvitXV_zM" />
            </links>
            <generos>
              <genero>Indie</genero>
              <genero>Alternative</genero>
              <genero>Folk</genero>
            </generos>
          </faixa>
          <faixa titulo="Lake House" duracao="275">
            <links>
              <link site="Spotify" logo="spotify.jpg" url="https://open.spotify.com/track/2TjLRCgnOwgNtmZ38OJ6pj" />
              <link site="YouTube" logo="youtube.jpg" url="https://www.youtube.com/watch?v=tBkkplOiSjQ" />
            </links>
            <generos>
              <genero>Indie</genero>
              <genero>Alternative</genero>
              <genero>Folk</genero>
            </generos>
          </faixa>
          <faixa titulo="Yellow Light" duracao="298">
            <links>
              <link site="Spotify" logo="spotify.jpg" url="https://open.spotify.com/track/3hs6kchwaeSe967AMMYTrp" />
              <link site="YouTube" logo="youtube.jpg" url="https://www.youtube.com/watch?v=aBlKPLeLU_s" />
            </links>
            <generos>
              <genero>Indie</genero>
              <genero>Alternative</genero>
              <genero>Folk</genero>
            </generos>
          </faixa>
        </faixas>
      </album>
      <album titulo="Beneath The Skin" imagem="beneath_OMAM.jpg" ano="2015" editora="Republic">
        <links>
          <link site="Amazon" logo="amazonLogo.jpg" url="https://www.amazon.com/Beneath-Skin-Monsters-Men/dp/B00US7OSEY" />
          <link site="iTunes" logo="iTunes.jpg" url="https://itunes.apple.com/ca/album/beneath-the-skin/id976392033" />
        </links>
        <faixas>
          <faixa titulo="Crystals" duracao="243">
            <links>
              <link site="Spotify" logo="spotify.jpg" url="https://open.spotify.com/track/1znRsYfVoNkIrh4ZfLFCoM" />
              <link site="YouTube" logo="youtube.jpg" url="https://www.youtube.com/watch?v=XUClIslXKZo" />
            </links>
            <generos>
              <genero>Alternative</genero>
              <genero>Indie</genero>
            </generos>
          </faixa>
          <faixa titulo="Human" duracao="233">
            <links>
              <link site="Spotify" logo="spotify.jpg" url="https://open.spotify.com/track/6k9eT9TVUBtFjWVr3TnCX3" />
              <link site="YouTube" logo="youtube.jpg" url="https://www.youtube.com/watch?v=0EnrFe3Zb6k" />
            </links>
            <generos>
              <genero>Alternative</genero>
              <genero>Indie</genero>
              <genero>Folk</genero>
            </generos>
          </faixa>
          <faixa titulo="Hunger" duracao="289">
            <links>
              <link site="Spotify" logo="spotify.jpg" url="https://open.spotify.com/track/7ybA0k82VI9u0GYdNKtzpF" />
              <link site="YouTube" logo="youtube.jpg" url="https://www.youtube.com/watch?v=n106Qo0D948" />
            </links>
            <generos>
              <genero>Alternative</genero>
              <genero>Indie</genero>
              <genero>Folk</genero>
            </generos>
          </faixa>
          <faixa titulo="Wolves Without Teeth" duracao="238">
            <links>
              <link site="Spotify" logo="spotify.jpg" url="https://open.spotify.com/track/2w8cJaVndSM5hPTiCzpQ0b" />
              <link site="YouTube" logo="youtube.jpg" url="https://www.youtube.com/watch?v=VAI5GSyXMjA" />
            </links>
            <generos>
              <genero>Alternative</genero>
              <genero>Indie</genero>
              <genero>Folk</genero>
            </generos>
          </faixa>
          <faixa titulo="Empire" duracao="460">
            <links>
              <link site="Spotify" logo="spotify.jpg" url="https://open.spotify.com/track/6nT4NFFH5nbXleO1FiJNhu" />
              <link site="YouTube" logo="youtube.jpg" url="https://www.youtube.com/watch?v=H2lzxGcbz-g" />
            </links>
            <generos>
              <genero>Alternative</genero>
              <genero>Indie</genero>
              <genero>Folk</genero>
            </generos>
          </faixa>
          <faixa titulo="Slow Life" duracao="343">
            <links>
              <link site="Spotify" logo="spotify.jpg" url="https://open.spotify.com/track/55pjgpQYWItjE2356fEFFY" />
              <link site="YouTube" logo="youtube.jpg" url="https://www.youtube.com/watch?v=XeZRJbB3_00" />
            </links>
            <generos>
              <genero>Alternative</genero>
              <genero>Indie</genero>
              <genero>Folk</genero>
            </generos>
          </faixa>
          <faixa titulo="Organs" duracao="271">
            <links>
              <link site="Spotify" logo="spotify.jpg" url="https://open.spotify.com/track/18EMlNlh7EMtw2jbu78WPk" />
              <link site="YouTube" logo="youtube.jpg" url="https://www.youtube.com/watch?v=hJZDHW6txk4" />
            </links>
            <generos>
              <genero>Alternative</genero>
              <genero>Indie</genero>
              <genero>Folk</genero>
            </generos>
          </faixa>
          <faixa titulo="Black Water" duracao="253">
            <links>
              <link site="Spotify" logo="spotify.jpg" url="https://open.spotify.com/track/1Jx5IdnXAJCKZ8EuczL5gX" />
              <link site="YouTube" logo="youtube.jpg" url="https://www.youtube.com/watch?v=AILsB9G8qEw" />
            </links>
            <generos>
              <genero>Alternative</genero>
              <genero>Indie</genero>
              <genero>Folk</genero>
            </generos>
          </faixa>
          <faixa titulo="Thousand Eyes" duracao="240">
            <links>
              <link site="Spotify" logo="spotify.jpg" url="https://open.spotify.com/track/2ulUHKORKH5Dfjg6CIFMLH" />
              <link site="YouTube" logo="youtube.jpg" url="https://www.youtube.com/watch?v=wylkSUS9Ofs" />
            </links>
            <generos>
              <genero>Alternative</genero>
              <genero>Indie</genero>
              <genero>Folk</genero>
            </generos>
          </faixa>
          <faixa titulo="I Of The Storm" duracao="276">
            <links>
              <link site="Spotify" logo="spotify.jpg" url="https://open.spotify.com/track/1y26LUkQmDtLvuy5xJZkVF" />
              <link site="YouTube" logo="youtube.jpg" url="https://www.youtube.com/watch?v=tlCkafSYNJI" />
            </links>
            <generos>
              <genero>Alternative</genero>
              <genero>Indie</genero>
              <genero>Folk</genero>
            </generos>
          </faixa>
          <faixa titulo="We Sink" duracao="261">
            <links>
              <link site="Spotify" logo="spotify.jpg" url="https://open.spotify.com/track/5Rme54e3v7rZkx3v8FkXLZ" />
              <link site="YouTube" logo="youtube.jpg" url="https://www.youtube.com/watch?v=dFRywBkXgdA" />
            </links>
            <generos>
              <genero>Alternative</genero>
              <genero>Indie</genero>
              <genero>Folk</genero>
            </generos>
          </faixa>
        </faixas>
      </album>
    </discografia>
    <biografia>
      <par>
        Of Monsters and Men is a five-member band from Reykjavík, Iceland, formed in 2010. The members are lead singer/guitarist Nanna Bryndís Hilmarsdóttir, co-singer-guitarist Ragnar "Raggi" Þórhallsson, guitarist Brynjar Leifsson, drummer Arnar Rósenkranz Hilmarsson and bassist Kristján Páll Kristjánsson. The band won the Músíktilraunir in 2010, an annual battle of the bands competition in Iceland. In 2011, Of Monsters and Men released an EP titled Into the Woods. The band's 2011 debut album My Head Is an Animal, reached the No.1 position in Australia, Iceland, Ireland and the U.S. Rock and Alternative Charts, while peaking at No. 6 on the U.S. Billboard 200 album chart, No. 3 in the UK, and Top 20 of most European charts and Canada. Its lead single "Little Talks" was an international success, reaching the Top 10 in most music charts in Europe, including No. 1 in Ireland and Iceland, and No. 1 on U.S. Alternative Songs.
      </par>
      <par>
        Of Monsters and Men won the 2013 European Border Breakers Awards.
      </par>
    </biografia>
  </banda>
  <banda nome="Imagine Dragons" imagem="dragons.jpg">
    <links>
      <link site="Wikipedia" logo="wikipediaLogo.jpg" url="https://en.wikipedia.org/wiki/Imagine_Dragons" />
      <link site="YouTube" logo="youtube.jpg" url="https://www.youtube.com/user/ImagineDragonsVEVO" />
      <link site="Imagine Dragons Site" logo="dragonsLogo.jpg" url="https://www.imaginedragonsmusic.com/" />
    </links>
    <membros>
      <membro nome="Dan Reynolds" foto="dan_Dragons.jpg" dataEntrada="2008" dataSaida="Present">
        <funcao>lead vocals</funcao>
        <funcao>rhythm guitar</funcao>
        <funcao>piano</funcao>
        <funcao>keyboards</funcao>
        <funcao>drums</funcao>
        <funcao>percussion</funcao>
      </membro>
      <membro nome="Wayne Sermon" foto="wayne_Dragons.jpg" dataEntrada="2009" dataSaida="Present">
        <funcao>lead guitar</funcao>
        <funcao>backing vocals</funcao>
        <funcao>mandolin</funcao>
      </membro>
      <membro nome="Ben McKee" foto="ben_Dragons.jpg" dataEntrada="2009" dataSaida="Present">
        <funcao>bass</funcao>
        <funcao>backing vocals</funcao>
        <funcao>piano</funcao>
        <funcao>keyboards</funcao>
        <funcao>synthesizers</funcao>
      </membro>
      <membro nome="Daniel Platzman" foto="daniel_Dragons.jpg" dataEntrada="2011" dataSaida="Present">
        <funcao>drums</funcao>
        <funcao>backing vocals</funcao>
        <funcao>percussion</funcao>
        <funcao>rhythm guitar</funcao>
        <funcao>synthesizers</funcao>
        <funcao>viola</funcao>
        <funcao>keyboards</funcao>
      </membro>
    </membros>
    <discografia>
      <album titulo="Night Visions" imagem="nightVisions_Dragons.jpg" ano="2012" editora="Various">
        <links>
          <link site="Amazon" logo="amazonLogo.jpg" url="https://www.amazon.com/Night-Visions-Imagine-Dragons/dp/B008K9SG9K" />
          <link site="iTunes" logo="iTunes.jpg" url="https://itunes.apple.com/us/album/night-visions/id555694735" />
        </links>
        <faixas>
          <faixa titulo="Radioactive" duracao="186">
            <links>
              <link site="Spotify" logo="spotify.jpg" url="https://open.spotify.com/track/62yJjFtgkhUrXktIoSjgP2" />
              <link site="YouTube" logo="youtube.jpg" url="https://www.youtube.com/watch?v=ktvTqknDobU" />
            </links>
            <generos>
              <genero>Rock</genero>
              <genero>Indie</genero>
              <genero>Eletro</genero>
            </generos>
          </faixa>
          <faixa titulo="Tiptoe" duracao="274">
            <links>
              <link site="Spotify" logo="spotify.jpg" url="https://open.spotify.com/track/7lBPn6LpIvbvAihTRvBMig" />
              <link site="YouTube" logo="youtube.jpg" url="https://www.youtube.com/watch?v=ajjj4pLnjz8" />
            </links>
            <generos>
              <genero>Rock</genero>
              <genero>Indie</genero>
              <genero>Eletro</genero>
            </generos>
          </faixa>
          <faixa titulo="It's Time" duracao="240">
            <links>
              <link site="Spotify" logo="spotify.jpg" url="https://open.spotify.com/track/7MXlTgQeo3IVlMpLnZuhxc" />
              <link site="YouTube" logo="youtube.jpg" url="https://www.youtube.com/watch?v=sENM2wA_FTg" />
            </links>
            <generos>
              <genero>Rock</genero>
              <genero>Indie</genero>
              <genero>Eletro</genero>
            </generos>
          </faixa>
          <faixa titulo="Demons" duracao="237">
            <links>
              <link site="Spotify" logo="spotify.jpg" url="https://open.spotify.com/track/5qaEfEh1AtSdrdrByCP7qR" />
              <link site="YouTube" logo="youtube.jpg" url="https://www.youtube.com/watch?v=mWRsgZuwf_8" />
            </links>
            <generos>
              <genero>Rock</genero>
              <genero>Indie</genero>
              <genero>Eletro</genero>
            </generos>
          </faixa>
          <faixa titulo="On Top Of The World" duracao="192">
            <links>
              <link site="Spotify" logo="spotify.jpg" url="https://open.spotify.com/track/213x4gsFDm04hSqIUkg88w" />
              <link site="YouTube" logo="youtube.jpg" url="https://www.youtube.com/watch?v=w5tWYmIOWGk" />
            </links>
            <generos>
              <genero>Rock</genero>
              <genero>Indie</genero>
              <genero>Eletro</genero>
            </generos>
          </faixa>
          <faixa titulo="Amsterdam" duracao="241">
            <links>
              <link site="Spotify" logo="spotify.jpg" url="https://open.spotify.com/track/5gXdinVZqeuDIVxogWzRk0" />
              <link site="YouTube" logo="youtube.jpg" url="https://www.youtube.com/watch?v=TKtPXO5iEnA" />
            </links>
            <generos>
              <genero>Rock</genero>
              <genero>Indie</genero>
              <genero>Eletro</genero>
            </generos>
          </faixa>
          <faixa titulo="Hear Me" duracao="235">
            <links>
              <link site="Spotify" logo="spotify.jpg" url="https://open.spotify.com/track/2OgOgEBfiZEj2XlIY2XD7f" />
              <link site="YouTube" logo="youtube.jpg" url="https://www.youtube.com/watch?v=1Yr683VLxes" />
            </links>
            <generos>
              <genero>Rock</genero>
              <genero>Indie</genero>
              <genero>Eletro</genero>
            </generos>
          </faixa>
          <faixa titulo="Every Night" duracao="217">
            <links>
              <link site="Spotify" logo="spotify.jpg" url="https://open.spotify.com/track/5raubQ8TVZTJO1PFs2bpwq" />
              <link site="YouTube" logo="youtube.jpg" url="https://www.youtube.com/watch?v=kuijhOvKyYg" />
            </links>
            <generos>
              <genero>Rock</genero>
              <genero>Indie</genero>
              <genero>Eletro</genero>
            </generos>
          </faixa>
          <faixa titulo="Bleedout" duracao="223">
            <links>
              <link site="Spotify" logo="spotify.jpg" url="https://open.spotify.com/track/1oQjPp1I7cwVE24JivbhzT" />
              <link site="YouTube" logo="youtube.jpg" url="https://www.youtube.com/watch?v=gJEoxeW7JvQ" />
            </links>
            <generos>
              <genero>Rock</genero>
              <genero>Indie</genero>
              <genero>Eletro</genero>
            </generos>
          </faixa>
          <faixa titulo="Underdoggo" duracao="209">
            <links>
              <link site="Spotify" logo="spotify.jpg" url="https://open.spotify.com/track/25dAGIi1Psxz5kzlNelPLN" />
              <link site="YouTube" logo="youtube.jpg" url="https://www.youtube.com/watch?v=JCUV43T7HZ0" />
            </links>
            <generos>
              <genero>Rock</genero>
              <genero>Indie</genero>
              <genero>Eletro</genero>
            </generos>
          </faixa>
        </faixas>
      </album>
      <album titulo="Smoke + Mirrors" imagem="smokeMirros_Dragons.jpg" ano="" editora="">
        <links>
          <link site="Amazon" logo="amazonLogo.jpg" url="https://www.amazon.com/Smoke-Mirrors-Imagine-Dragons/dp/B00QXKB7X0" />
          <link site="iTunes" logo="iTunes.jpg" url="https://itunes.apple.com/us/album/smoke-mirrors-deluxe/id1043732083" />
        </links>
        <faixas>
          <faixa titulo="Shots" duracao="232">
            <links>
              <link site="Spotify" logo="spotify.jpg" url="https://open.spotify.com/track/13rCBXMn31UOIXZBcjCOR3" />
              <link site="YouTube" logo="youtube.jpg" url="https://www.youtube.com/watch?v=qQrgto184Tk" />
            </links>
            <generos>
              <genero>Alternative</genero>
              <genero>Indie</genero>
              <genero>Rock</genero>
            </generos>
          </faixa>
          <faixa titulo="Gold" duracao="216">
            <links>
              <link site="Spotify" logo="spotify.jpg" url="https://open.spotify.com/track/6t7JWOqpPfzWGt51avo8H4" />
              <link site="YouTube" logo="youtube.jpg" url="https://www.youtube.com/watch?v=Rl3ELiPXFRo" />
            </links>
            <generos>
              <genero>Alternative</genero>
              <genero>Indie</genero>
              <genero>Rock</genero>
              <genero>Eletro</genero>
            </generos>
          </faixa>
          <faixa titulo="Smoke and Mirrors" duracao="260">
            <links>
              <link site="Spotify" logo="spotify.jpg" url="https://open.spotify.com/track/7fKnhuW1DlUWkKg5SeqSLX" />
              <link site="YouTube" logo="youtube.jpg" url="https://www.youtube.com/watch?v=VDPnaTQF6Dw" />
            </links>
            <generos>
              <genero>Alternative</genero>
              <genero>Indie</genero>
              <genero>Rock</genero>
              <genero>Eletro</genero>
            </generos>
          </faixa>
          <faixa titulo="I'm So Sorry" duracao="230">
            <links>
              <link site="Spotify" logo="spotify.jpg" url="https://open.spotify.com/track/0lbx84jPyJ9JKidRcrccgZ" />
              <link site="YouTube" logo="youtube.jpg" url="https://www.youtube.com/watch?v=D0gddT_DDzQ" />
            </links>
            <generos>
              <genero>Alternative</genero>
              <genero>Indie</genero>
              <genero>Rock</genero>
              <genero>Eletro</genero>
            </generos>
          </faixa>
          <faixa titulo="I Bet My Life" duracao="192">
            <links>
              <link site="Spotify" logo="spotify.jpg" url="https://open.spotify.com/track/0MbUlBzQuj4ayI1SGKJJep" />
              <link site="YouTube" logo="youtube.jpg" url="https://www.youtube.com/watch?v=4ht80uzIhNs" />
            </links>
            <generos>
              <genero>Alternative</genero>
              <genero>Indie</genero>
              <genero>Rock</genero>
            </generos>
          </faixa>
          <faixa titulo="Polariod" duracao="192">
            <links>
              <link site="Spotify" logo="spotify.jpg" url="https://open.spotify.com/track/5PBN3LsygMZLT2mvgACZlr" />
              <link site="YouTube" logo="youtube.jpg" url="https://www.youtube.com/watch?v=wmjyO-r1OhA" />
            </links>
            <generos>
              <genero>Alternative</genero>
              <genero>Indie</genero>
              <genero>Rock</genero>
              <genero>Eletro</genero>
            </generos>
          </faixa>
          <faixa titulo="Friction" duracao="201">
            <links>
              <link site="Spotify" logo="spotify.jpg" url="https://open.spotify.com/track/36UWrB0wlIUPuPDwH8JCa3" />
              <link site="YouTube" logo="youtube.jpg" url="https://www.youtube.com/watch?v=o0aoh363PI4" />
            </links>
            <generos>
              <genero>Alternative</genero>
              <genero>Indie</genero>
              <genero>Rock</genero>
              <genero>Eletro</genero>
            </generos>
          </faixa>
          <faixa titulo="It Comes Back To You" duracao="217">
            <links>
              <link site="Spotify" logo="spotify.jpg" url="https://open.spotify.com/track/7v2kIB8OoOIpF0o3P8ZXvn" />
              <link site="YouTube" logo="youtube.jpg" url="https://www.youtube.com/watch?v=xKkkIxSQ9wE" />
            </links>
            <generos>
              <genero>Alternative</genero>
              <genero>Indie</genero>
              <genero>Eletro</genero>
            </generos>
          </faixa>
          <faixa titulo="Dreams" duracao="258">
            <links>
              <link site="Spotify" logo="spotify.jpg" url="https://open.spotify.com/track/5hfKkcfjPlXvG4pSRJaPik" />
              <link site="YouTube" logo="youtube.jpg" url="https://www.youtube.com/watch?v=BWu7JDETw_I" />
            </links>
            <generos>
              <genero>Alternative</genero>
              <genero>Indie</genero>
              <genero>Eletro</genero>
            </generos>
          </faixa>
          <faixa titulo="Trouble" duracao="217">
            <links>
              <link site="Spotify" logo="spotify.jpg" url="https://open.spotify.com/track/2QX8fdouf5uSZVXZh97RcL" />
              <link site="YouTube" logo="youtube.jpg" url="https://www.youtube.com/watch?v=k4l5SLs5u8A" />
            </links>
            <generos>
              <genero>Alternative</genero>
              <genero>Indie</genero>
              <genero>Eletro</genero>
            </generos>
          </faixa>
          <faixa titulo="Summer" duracao="218">
            <links>
              <link site="Spotify" logo="spotify.jpg" url="https://open.spotify.com/track/6zM6FzZdnALCNXfW2dosao" />
              <link site="YouTube" logo="youtube.jpg" url="https://www.youtube.com/watch?v=kTsbz5fW8-M" />
            </links>
            <generos>
              <genero>Alternative</genero>
              <genero>Indie</genero>
              <genero>Eletro</genero>
            </generos>
          </faixa>
          <faixa titulo="Hopless Opus" duracao="238">
            <links>
              <link site="Spotify" logo="spotify.jpg" url="https://open.spotify.com/track/4yq2pwKWZmMODbJDTy45NP" />
              <link site="YouTube" logo="youtube.jpg" url="https://www.youtube.com/watch?v=QGnTR_oEFt4" />
            </links>
            <generos>
              <genero>Alternative</genero>
              <genero>Indie</genero>
              <genero>Eletro</genero>
            </generos>
          </faixa>
          <faixa titulo="The Fall" duracao="362">
            <links>
              <link site="Spotify" logo="spotify.jpg" url="https://open.spotify.com/track/42XaFrbjspn6Wkrv0bIhXg" />
              <link site="YouTube" logo="youtube.jpg" url="https://www.youtube.com/watch?v=8MWglxkw1y4" />
            </links>
            <generos>
              <genero>Alternative</genero>
              <genero>Indie</genero>
            </generos>
          </faixa>
        </faixas>
      </album>
      <album titulo="ƎVOLVE" imagem="evolve_Dragons.jpg" ano="2017" editora="Interscope">
        <links>
          <link site="Amazon" logo="amazonLogo.jpg" url="https://www.amazon.com/Evolve-Imagine-Dragons/dp/B07143J5MM/ref=pd_bxgy_15_img_2?_encoding=UTF8&amp;psc=1&amp;refRID=3NT47X08C6AF54MFP9ZH" />
          <link site="iTunes" logo="iTunes.jpg" url="https://itunes.apple.com/us/album/evolve/id1233502263" />
        </links>
        <faixas>
          <faixa titulo="I Don't Know Why" duracao="190">
            <links>
              <link site="Spotify" logo="spotify.jpg" url="https://open.spotify.com/track/15dnkAHcHC0vrIUlbiPiqU" />
              <link site="YouTube" logo="youtube.jpg" url="https://www.youtube.com/watch?v=izhxTx4LVWo" />
            </links>
            <generos>
              <genero>Alternative</genero>
              <genero>Indie</genero>
              <genero>Eletro</genero>
              <genero>House</genero>
            </generos>
          </faixa>
          <faixa titulo="Whatever It Takes" duracao="201">
            <links>
              <link site="Spotify" logo="spotify.jpg" url="https://open.spotify.com/track/4IWAyPf1KMq7JCyGeCjTeH" />
              <link site="YouTube" logo="youtube.jpg" url="https://www.youtube.com/watch?v=rGlEZpOVjGo" />
            </links>
            <generos>
              <genero>Alternative</genero>
              <genero>Indie</genero>
              <genero>Eletro</genero>
              <genero>Rap</genero>
            </generos>
          </faixa>
          <faixa titulo="Beliver" duracao="204">
            <links>
              <link site="Spotify" logo="spotify.jpg" url="https://open.spotify.com/track/0CcQNd8CINkwQfe1RDtGV6" />
              <link site="YouTube" logo="youtube.jpg" url="https://www.youtube.com/watch?v=7wtfhZwyrcc" />
            </links>
            <generos>
              <genero>Alternative</genero>
              <genero>Indie</genero>
              <genero>Eletro</genero>
              <genero>Rock</genero>
            </generos>
          </faixa>
          <faixa titulo="Walking The Wire" duracao="234">
            <links>
              <link site="Spotify" logo="spotify.jpg" url="https://open.spotify.com/track/6jmngk8Fwup05JZ6kgXEGX" />
              <link site="YouTube" logo="youtube.jpg" url="https://www.youtube.com/watch?v=1nv9br7P7g0" />
            </links>
            <generos>
              <genero>Alternative</genero>
              <genero>Indie</genero>
              <genero>Eletro</genero>
              <genero>Rock</genero>
            </generos>
          </faixa>
          <faixa titulo="Rise Up" duracao="231">
            <links>
              <link site="Spotify" logo="spotify.jpg" url="https://open.spotify.com/track/7vAXN57IQ0sj049wZGIboE" />
              <link site="YouTube" logo="youtube.jpg" url="https://www.youtube.com/watch?v=l7oOHT-1yxM" />
            </links>
            <generos>
              <genero>Alternative</genero>
              <genero>Indie</genero>
              <genero>Eletro</genero>
              <genero>House</genero>
            </generos>
          </faixa>
          <faixa titulo="I'll Make It Up To You" duracao="262">
            <links>
              <link site="Spotify" logo="spotify.jpg" url="https://open.spotify.com/track/54h8xHewdRPnYzmbEHBhOO" />
              <link site="YouTube" logo="youtube.jpg" url="https://www.youtube.com/watch?v=Qc78efgHMqo" />
            </links>
            <generos>
              <genero>Alternative</genero>
              <genero>Indie</genero>
              <genero>Eletro</genero>
              <genero>House</genero>
            </generos>
          </faixa>
          <faixa titulo="Yesterday" duracao="205">
            <links>
              <link site="Spotify" logo="spotify.jpg" url="https://open.spotify.com/track/7nXk8UzwYn0bKNH8NVz6xO" />
              <link site="YouTube" logo="youtube.jpg" url="https://www.youtube.com/watch?v=LeaydhTew3U" />
            </links>
            <generos>
              <genero>Alternative</genero>
              <genero>Indie</genero>
              <genero>Folk</genero>
              <genero>Rock</genero>
            </generos>
          </faixa>
          <faixa titulo="Mouth Of The River" duracao="221">
            <links>
              <link site="Spotify" logo="spotify.jpg" url="https://open.spotify.com/track/6dSKDp21S6I5UOhDqjw4kB" />
              <link site="YouTube" logo="youtube.jpg" url="https://www.youtube.com/watch?v=gJf9TMk6y-Y" />
            </links>
            <generos>
              <genero>Alternative</genero>
              <genero>Indie</genero>
              <genero>Eletro</genero>
              <genero>Rock</genero>
            </generos>
          </faixa>
          <faixa titulo="Start Over" duracao="306">
            <links>
              <link site="Spotify" logo="spotify.jpg" url="https://open.spotify.com/track/6Q9ue1D2FU489FD4Uln3SX" />
              <link site="YouTube" logo="youtube.jpg" url="https://www.youtube.com/watch?v=qCHzOFEkyZ8" />
            </links>
            <generos>
              <genero>Alternative</genero>
              <genero>Indie</genero>
              <genero>Eletro</genero>
            </generos>
          </faixa>
          <faixa titulo="Dancing In The Dark" duracao="234">
            <links>
              <link site="Spotify" logo="spotify.jpg" url="https://open.spotify.com/track/5HvtbJxOYLSACcPuhf62wT" />
              <link site="YouTube" logo="youtube.jpg" url="https://www.youtube.com/watch?v=f242R8si7qU" />
            </links>
            <generos>
              <genero>Alternative</genero>
              <genero>Indie</genero>
              <genero>Eletro</genero>
            </generos>
          </faixa>
        </faixas>
      </album>
    </discografia>
    <biografia>
      <par>
        Imagine Dragons is an American rock band from Las Vegas, Nevada, consisting of lead vocalist Dan Reynolds, lead guitarist Wayne Sermon, bassist and keyboardist Ben McKee, and drummer Daniel Platzman. The band first gained exposure in 2012 with the releases of their debut studio album Night Visions and its first single "It's Time". Billboard placed them at the top of their "Year In Rock" rankings for 2013, and named them their "Breakthrough Band of 2013". Rolling Stone named their single "Radioactive" from Night Visions the "biggest rock hit of the year", and MTV called them "the year's biggest breakout band". Night Visions peaked at number two on the weekly US Billboard 200 chart and the UK Albums Chart. The band's second studio album Smoke + Mirrors was released in 2015, and reached number one in the US, Canada and the UK. After touring for their sophomore record, the band took a brief hiatus to focus on their personal lives. During the latter half of 2016, they began recording their third studio album, Evolve, released in 2017. While all three albums were commercially successful, critical reception was mixed.
      </par>
      <par>
        Imagine Dragons has won two American Music Awards for Favorite Alternative Artist, a Grammy Award for Best Rock Performance, five Billboard Music Awards, and a World Music Award. In May 2014, the band was nominated for a total of fourteen different Billboard Music Awards, including Top Artist of the Year and a Milestone Award, which recognizes innovation and creativity of artists across different genres. Imagine Dragons have sold 9 million albums and 27 million singles worldwide.
      </par>
    </biografia>
  </banda>
  <banda nome="TWRP" imagem="twrp.jpg">
    <links>
      <link site="Wikipedia" logo="wikipediaLogo.jpg" url="http://www.allmusic.com/artist/twrp-mn0003591623/biography" />
      <link site="YouTube" logo="youtube.jpg" url="https://www.youtube.com/user/TWRPtube" />
      <link site="TWRP Site" logo="twrpLogo.jpg" url="https://twrp.bandcamp.com/" />
    </links>
    <membros>
      <membro nome="Doctor Sung" foto="sung_TWRP.jpg" dataEntrada="2011" dataSaida="Present">
        <funcao>vocals</funcao>
        <funcao>talk box</funcao>
        <funcao>keytar</funcao>
      </membro>
      <membro nome="Lord Phobos" foto="phobos_TWRP.jpg" dataEntrada="2011" dataSaida="Present">
        <funcao>guitar</funcao>
      </membro>
      <membro nome="Commander Meouch" foto="meouch_TWRP.jpg" dataEntrada="2011" dataSaida="Present">
        <funcao>bass</funcao>
      </membro>
      <membro nome="Havve Hogan" foto="hogan_TWRP.jpg" dataEntrada="2011" dataSaida="Present">
        <funcao>drums</funcao>
      </membro>
    </membros>
    <discografia>
      <album titulo="The Device" imagem="device_TWRP.jpg" ano="2015" editora="Independent">
        <links>
          <link site="Amazon" logo="amazonLogo.jpg" url="https://www.amazon.com/gp/product/B013RKSPAQ/ref=dm_ws_sp_ps_dp" />
          <link site="iTunes" logo="iTunes.jpg" url="https://itunes.apple.com/us/album/the-device-ep/id1023614590" />
        </links>
        <faixas>
          <faixa titulo="Prelude" duracao="86">
            <links>
              <link site="Spotify" logo="spotify.jpg" url="https://open.spotify.com/track/3BvPejrfGaGK05Jd3rAJWE" />
              <link site="YouTube" logo="youtube.jpg" url="https://www.youtube.com/watch?v=j5CKFyff4i4" />
            </links>
            <generos>
              <genero>Rock</genero>
              <genero>Funk</genero>
              <genero>Eletro</genero>
            </generos>
          </faixa>
          <faixa titulo="Computer Wife" duracao="260">
            <links>
              <link site="Spotify" logo="spotify.jpg" url="https://open.spotify.com/track/7MQppNMiujzmo4h0MRh134" />
              <link site="YouTube" logo="youtube.jpg" url="https://www.youtube.com/watch?v=X3rp-h69aTk" />
            </links>
            <generos>
              <genero>Rock</genero>
              <genero>Funk</genero>
              <genero>Eletro</genero>
            </generos>
          </faixa>
          <faixa titulo="Interstelar Strut" duracao="170">
            <links>
              <link site="Spotify" logo="spotify.jpg" url="https://open.spotify.com/track/14k0Ekc0YxNn56OLtGJTLB" />
              <link site="YouTube" logo="youtube.jpg" url="https://www.youtube.com/watch?v=jLzULI84rLE" />
            </links>
            <generos>
              <genero>Rock</genero>
              <genero>Funk</genero>
              <genero>Eletro</genero>
            </generos>
          </faixa>
          <faixa titulo="No Pants Dance" duracao="271">
            <links>
              <link site="Spotify" logo="spotify.jpg" url="https://open.spotify.com/track/4jvhvClPrHxR6ozO0kcXSI" />
              <link site="YouTube" logo="youtube.jpg" url="https://www.youtube.com/watch?v=FP5BXlPhy8Y" />
            </links>
            <generos>
              <genero>Rock</genero>
              <genero>Funk</genero>
              <genero>Eletro</genero>
            </generos>
          </faixa>
          <faixa titulo="The Device Pt 1" duracao="232">
            <links>
              <link site="Spotify" logo="spotify.jpg" url="https://open.spotify.com/track/3eSTEEI4PgnS5CiHDBEWFV" />
              <link site="YouTube" logo="youtube.jpg" url="https://www.youtube.com/watch?v=6xE72cKW5_4" />
            </links>
            <generos>
              <genero>Rock</genero>
              <genero>Funk</genero>
              <genero>Eletro</genero>
            </generos>
          </faixa>
          <faixa titulo="The Device Pt 2" duracao="239">
            <links>
              <link site="Spotify" logo="spotify.jpg" url="https://open.spotify.com/track/0J6EdykQw1UTFc4wjhNjmv" />
              <link site="YouTube" logo="youtube.jpg" url="https://www.youtube.com/watch?v=0N9R8Q6cR7U" />
            </links>
            <generos>
              <genero>Rock</genero>
              <genero>Funk</genero>
              <genero>Eletro</genero>
            </generos>
          </faixa>
        </faixas>
      </album>
      <album titulo="Guardians of the Zone" imagem="guardians_TWRP.jpg" ano="2016" editora="Independent">
        <links>
          <link site="Amazon" logo="amazonLogo.jpg" url="https://www.amazon.com/Guardians-Zone-Twrp/dp/B01EG0STMA" />
          <link site="iTunes" logo="iTunes.jpg" url="https://itunes.apple.com/us/album/guardians-of-the-zone-ep/id1104884346" />
        </links>
        <faixas>
          <faixa titulo="Time To Shine" duracao="160">
            <links>
              <link site="Spotify" logo="spotify.jpg" url="https://open.spotify.com/track/0pLKXolufs3kpPuxrR085Y" />
              <link site="YouTube" logo="youtube.jpg" url="https://www.youtube.com/watch?v=I-6UDp7uOIk" />
            </links>
            <generos>
              <genero>Rock</genero>
              <genero>Synth</genero>
              <genero>Funk</genero>
            </generos>
          </faixa>
          <faixa titulo="Rock n Roll Best Friends" duracao="215">
            <links>
              <link site="Spotify" logo="spotify.jpg" url="https://open.spotify.com/track/0WOH3hD4pIw9YyTsiZFZ5j" />
              <link site="YouTube" logo="youtube.jpg" url="https://www.youtube.com/watch?v=0PHMkR-RHA8" />
            </links>
            <generos>
              <genero>Rock</genero>
              <genero>Synth</genero>
              <genero>Funk</genero>
            </generos>
          </faixa>
          <faixa titulo="Making A Move" duracao="249">
            <links>
              <link site="Spotify" logo="spotify.jpg" url="https://open.spotify.com/track/1Ea64ROQHsFNdB1U0EqEgf" />
              <link site="YouTube" logo="youtube.jpg" url="https://www.youtube.com/watch?v=-RE6EuHyjU8" />
            </links>
            <generos>
              <genero>Rock</genero>
              <genero>Synth</genero>
              <genero>Funk</genero>
            </generos>
          </faixa>
          <faixa titulo="No Pants Dance (ft. NSP)" duracao="266">
            <links>
              <link site="Spotify" logo="spotify.jpg" url="https://open.spotify.com/track/1oljsr7HuLJxHdlC1cIxA2" />
              <link site="YouTube" logo="youtube.jpg" url="https://www.youtube.com/watch?v=YyGMsaGOjpc" />
            </links>
            <generos>
              <genero>Rock</genero>
              <genero>Synth</genero>
              <genero>Funk</genero>
            </generos>
          </faixa>
          <faixa titulo="Business Tips" duracao="165">
            <links>
              <link site="Spotify" logo="spotify.jpg" url="https://open.spotify.com/track/2BjalCX3MMlfDWq6N4ZGXO" />
              <link site="YouTube" logo="youtube.jpg" url="https://www.youtube.com/watch?v=oUKLaPmvP84" />
            </links>
            <generos>
              <genero>Rock</genero>
              <genero>Synth</genero>
              <genero>Funk</genero>
            </generos>
          </faixa>
          <faixa titulo="Groove Crusaders" duracao="260">
            <links>
              <link site="Spotify" logo="spotify.jpg" url="https://open.spotify.com/track/0TtNiDIU5UgxvGUHiJmXsx" />
              <link site="YouTube" logo="youtube.jpg" url="https://www.youtube.com/watch?v=VBxDiBxMF-g" />
            </links>
            <generos>
              <genero>Rock</genero>
              <genero>Synth</genero>
              <genero>Eletro</genero>
              <genero>Funk</genero>
            </generos>
          </faixa>
        </faixas>
      </album>
      <album titulo="Ladyworld" imagem="ladyworld_TWRP.jpg" ano="2017" editora="Independent">
        <links>
          <link site="Amazon" logo="amazonLogo.jpg" url="https://www.amazon.com/Ladyworld-Twrp/dp/B01N0XO2MN" />
          <link site="iTunes" logo="iTunes.jpg" url="https://itunes.apple.com/us/album/ladyworld/id1192111721" />
        </links>
        <faixas>
          <faixa titulo="Overture" duracao="96">
            <links>
              <link site="Spotify" logo="spotify.jpg" url="https://open.spotify.com/track/3bCk3fngYvnd2OPXUqSxcE" />
              <link site="YouTube" logo="youtube.jpg" url="https://www.youtube.com/watch?v=R1xAggBGqDE" />
            </links>
            <generos>
              <genero>Rock</genero>
              <genero>Funk</genero>
              <genero>Eletro</genero>
            </generos>
          </faixa>
          <faixa titulo="Ladyworld" duracao="257">
            <links>
              <link site="Spotify" logo="spotify.jpg" url="https://open.spotify.com/track/2bVBqvMa0ssrxdWNYpWqJK" />
              <link site="YouTube" logo="youtube.jpg" url="https://www.youtube.com/watch?v=xBYcwn8sa4E" />
            </links>
            <generos>
              <genero>Rock</genero>
              <genero>Funk</genero>
              <genero>Eletro</genero>
            </generos>
          </faixa>
          <faixa titulo="R.E.S.P.E.C.T. Her" duracao="164">
            <links>
              <link site="Spotify" logo="spotify.jpg" url="https://open.spotify.com/track/5Btz2Ubj8P5gg3eZdeDabs" />
              <link site="YouTube" logo="youtube.jpg" url="https://www.youtube.com/watch?v=mZvMfIF8PFw" />
            </links>
            <generos>
              <genero>Rock</genero>
              <genero>Funk</genero>
              <genero>Eletro</genero>
            </generos>
          </faixa>
          <faixa titulo="Atomic Karate" duracao="241">
            <links>
              <link site="Spotify" logo="spotify.jpg" url="https://open.spotify.com/track/59m6MeVQeeK9lucs8ZKOmp" />
              <link site="YouTube" logo="youtube.jpg" url="https://www.youtube.com/watch?v=V4tSXOLPf_4" />
            </links>
            <generos>
              <genero>Rock</genero>
              <genero>Funk</genero>
              <genero>Eletro</genero>
            </generos>
          </faixa>
          <faixa titulo="Body Image" duracao="261">
            <links>
              <link site="Spotify" logo="spotify.jpg" url="https://open.spotify.com/track/2Bro9LaruzR6FLyjizU1Pt" />
              <link site="YouTube" logo="youtube.jpg" url="https://www.youtube.com/watch?v=GK2aXhG3iqk" />
            </links>
            <generos>
              <genero>Rock</genero>
              <genero>Funk</genero>
              <genero>Eletro</genero>
            </generos>
          </faixa>
          <faixa titulo="Food Bar" duracao="199">
            <links>
              <link site="Spotify" logo="spotify.jpg" url="https://open.spotify.com/track/3HIK2cfukdovoKr8gRzYNx" />
              <link site="YouTube" logo="youtube.jpg" url="https://www.youtube.com/watch?v=JpaXl8CdwzM" />
            </links>
            <generos>
              <genero>Rock</genero>
              <genero>Funk</genero>
              <genero>Eletro</genero>
            </generos>
          </faixa>
          <faixa titulo="Built 4 Love (ft. NSP)" duracao="199">
            <links>
              <link site="Spotify" logo="spotify.jpg" url="https://open.spotify.com/track/5Q8IYNSjOjwzFGKMfmrAdK" />
              <link site="YouTube" logo="youtube.jpg" url="https://www.youtube.com/" />
            </links>
            <generos>
              <genero>Rock</genero>
              <genero>Funk</genero>
              <genero>Eletro</genero>
            </generos>
          </faixa>
          </faixas>
      </album>
    </discografia>
    <biografia>
      <par>Although they're based in Toronto, Canada, '80s-inspired synth rock/electro funk outfit TWRP ("Tupper Ware Remix Party") transcend time and space. Known for their wild live shows and unpretentious party music, TWRP was created by frontman, vocalist, and keytar wielder Doctor Sung, who was born around the time of the Big Bang. The 69th degree black belt recruited the group's second member, robot drummer Havve Hogan, sometime during the Mesozoic Era. The pair would not fully flesh out the band until much later, when the lion-headed, intergalactic, funk-smuggling humanoid Commander Meouch joined as TWRP's bassist and the fourth and final member, rocketeering Lord Phobos, filled the guitarist slot. Together, the four spandex-clad time-and-space travelers made their debut in 2011 with the "Lazerhorse" single, a combination of melodic chiptune and '80s hair metal. The following year, TWRP unveiled their first funky EP, The Device, which saw the quartet develop their sound in the direction of a Discovery-era Daft Punk cover band. A pair of EPs arrived in 2015. 2nite featured appearances by Skratch Bastid and NSP, an American duo who would become frequent collaborators with TWRP. Another NSP track was included on 2015's other EP, Believe in Your Dreams, which also featured White Hot Guilt. TWRP's first extended collaboration with NSP was released in 2016. The Under the Covers EP included their interpretations of '80s classics from a-ha, Tears for Fears, Van Halen, Michael Jackson, and others, with TWRP serving as the duo's backing band. TWRP released their fourth EP that year as well. Guardians of the Zone included "Rock n Roll Best Friends" and an updated version of The Device's "The No Pants Dance" that added NSP to the mix. In early 2017, their fifth effort arrived. Ladyworld debuted at number five on the Billboard Heatseekers chart.</par>
    </biografia>
  </banda>
</bandas>

<!--
	<banda nome="" imagem="">
		<links>
			<link site="Wikipedia" logo="wikipediaLogo.jpg" url="" />
			<link site="YouTube" logo="youtube.jpg" url="" />
      <link site="" logo="banda.jpg" url="" />
		</links>
		<membros>
			<membro nome="" foto="" dataEntrada="" dataSaida="">
				<funcao>funcao</funcao>
			</membro>
		</membros>
		<discografia>
			<album titulo="" imagem="" ano="" editora="">
				<links>
					<link site="Amazon" logo="amazonLogo.jpg" url="" />
					<link site="iTunes" logo="iTunes.jpg" url="" />
				</links>
				<faixas>
					<faixa titulo="" duracao="">
						<links>
							<link site="Spotify" logo="spotify.jpg" url="" />
							<link site="YouTube" logo="youtube.jpg" url="" />
						</links>
						<generos>
							<genero>genero</genero>
						</generos>
					</faixa>
				</faixas>
			</album>
		</discografia>
		<biografia>
			<par>bioPar</par>
		</biografia>
	</banda>
-->
